heatmapanimation/__init__.py
heatmapanimation/heatmap.py
heatmapanimation-0.0.6.dist-info/LICENSE
heatmapanimation-0.0.6.dist-info/METADATA
heatmapanimation-0.0.6.dist-info/WHEEL
heatmapanimation-0.0.6.dist-info/top_level.txt
heatmapanimation-0.0.6.dist-info/RECORD
